{
  "tids": [
    "30010100",
    "30010200",
    "30020100",
    "30030100",
    "30040100",
    "30050100",
    "30990100"
  ],
  "result": {
    "30010100": {
      "_tid": "30010100",
      "familyCode": 30,
      "skillCode": 1,
      "levelCode": 1,
      "variantCode": 0,
      "sequence": 1,
      "name": "Molten Bulwark",
      "tag": "Support",
      "target": "AllyTeam",
      "cooldown": 10,
      "energyCost": 20,
      "formula": "Basic",
      "power": 1,
      "description": "为全队提供护盾并反弹20%伤害。"
    },
    "30010200": {
      "_tid": "30010200",
      "familyCode": 30,
      "skillCode": 1,
      "levelCode": 2,
      "variantCode": 0,
      "sequence": 2,
      "name": "Molten Bulwark+",
      "tag": "Support",
      "target": "AllyTeam",
      "cooldown": 8,
      "energyCost": 20,
      "formula": "Basic",
      "power": 1.2,
      "description": "护盾强化，并赋予护盾破裂爆炸。"
    },
    "30020100": {
      "_tid": "30020100",
      "familyCode": 30,
      "skillCode": 2,
      "levelCode": 1,
      "variantCode": 0,
      "sequence": 1,
      "name": "Starfall Spear",
      "tag": "Spell",
      "target": "Enemy",
      "cooldown": 12,
      "energyCost": 30,
      "formula": "Burst",
      "power": 1.35,
      "description": "召唤星辉长枪，对单体造成高额伤害。"
    },
    "30030100": {
      "_tid": "30030100",
      "familyCode": 30,
      "skillCode": 3,
      "levelCode": 1,
      "variantCode": 0,
      "sequence": 1,
      "name": "Gravity Lattice",
      "tag": "Control",
      "target": "EnemyAll",
      "cooldown": 13,
      "energyCost": 28,
      "formula": "Aoe",
      "power": 0.95,
      "description": "放置重力锁阵，降低敌方速度并造成持续伤害。"
    },
    "30040100": {
      "_tid": "30040100",
      "familyCode": 30,
      "skillCode": 4,
      "levelCode": 1,
      "variantCode": 0,
      "sequence": 1,
      "name": "Echo Barrage",
      "tag": "Ranged",
      "target": "Enemy",
      "cooldown": 9,
      "energyCost": 16,
      "formula": "Pierce",
      "power": 1.1,
      "description": "连续射击，命中同一目标时累计易伤。"
    },
    "30050100": {
      "_tid": "30050100",
      "familyCode": 30,
      "skillCode": 5,
      "levelCode": 1,
      "variantCode": 0,
      "sequence": 1,
      "name": "Verdant Pulse",
      "tag": "Support",
      "target": "AllyTeam",
      "cooldown": 11,
      "energyCost": 18,
      "formula": "Basic",
      "power": 0.8,
      "description": "治愈并赋予再生，若目标携带藤蔓印记则额外回复。"
    },
    "30990100": {
      "_tid": "30990100",
      "familyCode": 30,
      "skillCode": 99,
      "levelCode": 1,
      "variantCode": 0,
      "sequence": 1,
      "name": "Crucible Overload",
      "tag": "Spell",
      "target": "EnemyAll",
      "cooldown": 16,
      "energyCost": 40,
      "formula": "Burst",
      "power": 1.6,
      "description": "极限释放，爆发星火冲击全场。"
    }
  },
  "collisions": [],
  "meta": {
    "idSegments": [
      0,
      1,
      2,
      3
    ],
    "markCols": [
      "A",
      "B",
      "C",
      "D",
      "E",
      "F",
      "G",
      "H",
      "I",
      "J",
      "K",
      "L",
      "M"
    ]
  }
}